webpify/__init__.py
webpify/__main__.py
webpify/webpify.py
webpify-2.0.0.dist-info/LICENSE
webpify-2.0.0.dist-info/METADATA
webpify-2.0.0.dist-info/WHEEL
webpify-2.0.0.dist-info/RECORD
