Metadata-Version: 2.3
Name: webpify
Version: 2.0.0
Summary: Converts images to webp from CLI using Python/Pillow.
License: MIT
Author: Matt Lucero
Author-email: matt_lucero@outlook.com
Requires-Python: >=3.9
Classifier: License :: OSI Approved :: MIT License
Classifier: Programming Language :: Python :: 3
Classifier: Programming Language :: Python :: 3.9
Classifier: Programming Language :: Python :: 3.10
Classifier: Programming Language :: Python :: 3.11
Classifier: Programming Language :: Python :: 3.12
Classifier: Programming Language :: Python :: 3.13
Requires-Dist: pillow (>=11.1.0,<12.0.0)
Requires-Dist: tqdm (>=4.67.1,<5.0.0)
